{"Type": "CURRENCY","Key": "IX1","MetaData": {"Folder":"","Id":"IX1","Name":"!!!FOR UNIT TEST!!!"},"ConfigurationDependencies": {"YCMDEF": ["IX1"],"DISCCONVENTIONS": ["IX1"]},"TableDependencies": null,"InstallationChecks": null,"Attributes": {"pCUR": "IX1","pCURNAME": "!!!FOR UNIT TEST!!!","pSORT": null,"pYCIK-pYC": "IX1","pDECIMALS": 0,"pDISCCONVIK-pDISCCONV": "IX1","pEXTCUR": "","pFXEUROFROM": null,"pHIDDEN": false,"pCALIK-pCAL": "","pCURSTLMDAYS": null,"pCURFC1": null,"pCURFC2": "","pCURFC3": "","pCURFC4": "","pCURFC5": "","pCURFC6": "","pCURFC7": "","pCURFC8": "","pISDACUR": [0,"(none)"],"pCUTOFF": false,"pUSECALFORIMM": false}}