{"Type": "CURRENCY","Key": "S28","MetaData": {"Folder":"","Id":"S28","Name":"test"},"ConfigurationDependencies": {"DISCCONVENTIONS": ["ALSDISC"],"CALENDARS": ["211"]},"TableDependencies": null,"InstallationChecks": null,"Attributes": {"pCUR": "S28","pCURNAME": "test","pSORT": null,"pYCIK-pYC": "","pDECIMALS": 0,"pDISCCONVIK-pDISCCONV": "ALSDISC","pEXTCUR": "","pFXEUROFROM": null,"pHIDDEN": false,"pCALIK-pCAL": "211","pCURSTLMDAYS": null,"pCURFC1": null,"pCURFC2": "","pCURFC3": "","pCURFC4": "","pCURFC5": "","pCURFC6": "","pCURFC7": "","pCURFC8": "","pISDACUR": [0,"(none)"],"pCUTOFF": false,"pUSECALFORIMM": false}}